{
    "Ar36": {
        "error": 0.0012051664341367647,
        "error_type": "SEM",
        "filter_outliers_dict": {
            "filter_outliers": true,
            "iterations": 1,
            "std_devs": 3,
            "use_iqr_filtering": false,
            "use_standard_deviation_filtering": false
        },
        "fit": "parabolic",
        "fn": 340,
        "include_baseline_error": false,
        "n": 340,
        "outlier_excluded": [],
        "reviewed": true,
        "user_excluded": [],
        "value": 0.19281205888259287
    },
    "Ar37": {
        "error": 0.016819913957363358,
        "error_type": "SEM",
        "filter_outliers_dict": {
            "filter_outliers": true,
            "iterations": 1,
            "std_devs": 3,
            "use_iqr_filtering": false,
            "use_standard_deviation_filtering": false
        },
        "fit": "linear",
        "fn": 338,
        "include_baseline_error": false,
        "n": 340,
        "outlier_excluded": [
            1,
            199
        ],
        "reviewed": true,
        "user_excluded": [],
        "value": 1.1836035611920304
    },
    "Ar38": {
        "error": 0.005622709477678692,
        "error_type": "SEM",
        "filter_outliers_dict": {
            "filter_outliers": true,
            "iterations": 1,
            "std_devs": 3,
            "use_iqr_filtering": false,
            "use_standard_deviation_filtering": false
        },
        "fit": "linear",
        "fn": 339,
        "include_baseline_error": false,
        "n": 340,
        "outlier_excluded": [
            337
        ],
        "reviewed": true,
        "user_excluded": [],
        "value": 0.5301318738022217
    },
    "Ar39": {
        "error": 0.016924151160172145,
        "error_type": "SEM",
        "filter_outliers_dict": {
            "filter_outliers": true,
            "iterations": 1,
            "std_devs": 3,
            "use_iqr_filtering": false,
            "use_standard_deviation_filtering": false
        },
        "fit": "parabolic",
        "fn": 339,
        "include_baseline_error": false,
        "n": 340,
        "outlier_excluded": [
            267
        ],
        "reviewed": true,
        "user_excluded": [],
        "value": 28.547730523854703
    },
    "Ar40": {
        "error": 0.048111746569614894,
        "error_type": "SEM",
        "filter_outliers_dict": {
            "filter_outliers": true,
            "iterations": 1,
            "std_devs": 3,
            "use_iqr_filtering": false,
            "use_standard_deviation_filtering": false
        },
        "fit": "parabolic",
        "fn": 340,
        "include_baseline_error": false,
        "n": 340,
        "outlier_excluded": [],
        "reviewed": true,
        "user_excluded": [],
        "value": 265.43454160015125
    }
}